{"Area":{"0":"Brazil","1":"France","2":"South Korea","3":"China","4":"United Kingdom","5":"Mexico","6":"Germany","7":"Italy","8":"Australia","9":"Spain","10":"Vietnam","11":"Argentina","12":"Chile","13":"Japan","14":"Belgium","15":"Taiwan","16":"Colombia","17":"Switzerland","18":"Denmark","19":"Poland","20":"New Zealand","21":"Austria","22":"Philippines","23":"Norway","24":"Singapore","25":"Russia\/CIS","26":"Indonesia","27":"Malaysia","28":"India","29":"Thailand","30":"Netherlands","31":"Croatia","32":"Finland","33":"Sweden","34":"Hong Kong","35":"United Arab Emirates","36":"Israel","37":"T\u00fcrkiye","38":"Portugal","39":"Ecuador","40":"South Africa","41":"Hungary","42":"Slovakia","43":"Bolivia","44":"Romania","45":"Uruguay","46":"Czech Republic","47":"Bulgaria","48":"Serbia and Montenegro","49":"Iceland","50":"Slovenia","51":"Ukraine","52":"Saudi Arabia","53":"Kenya","54":"Central America","55":"Albania","56":"Greece","57":"North Macedonia","58":"Nigeria","59":"Peru","60":"Estonia","61":"Lithuania","62":"Cyprus","63":"Egypt","64":"Latvia","65":"Lebanon","66":"Pakistan","67":"Sri Lanka"},"Weekend":{"0":"Jul 4-7","1":"Jul 3-7","2":"Jul 5-7","3":"Jul 5-7","4":"Jul 5-7","5":"Jul 5-7","6":"Jul 4-7","7":"Jul 4-7","8":"Jul 4-7","9":"Jul 5-7","10":"Jul 5-7","11":"Jul 4-7","12":"Jul 4-7","13":"Jul 6-7","14":"Jul 3-7","15":"Jul 5-7","16":"Jul 4-7","17":"Jul 3-7","18":"Jul 4-7","19":"Jul 5-7","20":"Jul 4-7","21":"Jul 4-7","22":"Jul 3-7","23":"Jul 5-7","24":"Jul 4-7","25":"Jul 4-7","26":"Jul 3-7","27":"Jul 4-7","28":"Jul 5-7","29":"Jul 4-7","30":"Jul 4-7","31":"Jul 4-7","32":"Jul 5-7","33":"Jul 5-7","34":"Jul 4-7","35":"Jun 27-30","36":"Jun 27-30","37":"Jun 28-30","38":"Jun 27-30","39":"Jun 28-30","40":"Jun 28-30","41":"Jun 27-30","42":"Jun 27-30","43":"Jun 27-30","44":"Jun 28-30","45":"Jun 27-30","46":"Jun 27-30","47":"Jun 28-30","48":"Jun 27-30","49":"Jun 28-30","50":"Jun 27-30","51":"Jun 27-30","52":"Jun 27-30","53":"Jun 26-30","54":"Jun 27-30","55":"Jun 29-30","56":"Jun 27-30","57":"Jun 28-30","58":"Jun 26-30","59":"Jun 27-30","60":"Jun 28-30","61":"Jun 28-30","62":"Jun 28-30","63":"Jun 26-30","64":"Jun 28-30","65":"Jun 27-30","66":"Jun 26-30","67":"Jun 28-30"},"Releases":{"0":4,"1":3,"2":2,"3":3,"4":3,"5":2,"6":11,"7":21,"8":2,"9":3,"10":18,"11":2,"12":2,"13":11,"14":3,"15":2,"16":2,"17":3,"18":3,"19":2,"20":2,"21":3,"22":2,"23":3,"24":2,"25":125,"26":2,"27":2,"28":3,"29":2,"30":2,"31":20,"32":2,"33":2,"34":1,"35":40,"36":16,"37":54,"38":49,"39":13,"40":21,"41":54,"42":28,"43":13,"44":36,"45":12,"46":29,"47":74,"48":10,"49":24,"50":24,"51":13,"52":10,"53":10,"54":12,"55":11,"56":12,"57":10,"58":10,"59":12,"60":12,"61":12,"62":11,"63":10,"64":12,"65":10,"66":8,"67":8},"#1 Release":{"0":"Inside Out 2","1":"Inside Out 2","2":"Inside Out 2","3":"Inside Out 2","4":"Inside Out 2","5":"Inside Out 2","6":"Inside Out 2","7":"Inside Out 2","8":"Inside Out 2","9":"Inside Out 2","10":"Despicable Me 4","11":"Inside Out 2","12":"Inside Out 2","13":"Look Back","14":"Inside Out 2","15":"Inside Out 2","16":"Inside Out 2","17":"Inside Out 2","18":"Inside Out 2","19":"Inside Out 2","20":"Inside Out 2","21":"Inside Out 2","22":"Inside Out 2","23":"Inside Out 2","24":"Inside Out 2","25":"Tri bogatyrya. Ni dnya bez podviga","26":"Inside Out 2","27":"Inside Out 2","28":"Inside Out 2","29":"Inside Out 2","30":"Kinds of Kindness","31":"Despicable Me 4","32":"Kinds of Kindness","33":"Kingdom of the Planet of the Apes","34":"Kingdom of the Planet of the Apes","35":"Inside Out 2","36":"Despicable Me 4","37":"Inside Out 2","38":"Despicable Me 4","39":"Despicable Me 4","40":"Despicable Me 4","41":"Inside Out 2","42":"Inside Out 2","43":"Despicable Me 4","44":"Inside Out 2","45":"Despicable Me 4","46":"A Quiet Place: Day One","47":"Inside Out 2","48":"Despicable Me 4","49":"Inside Out 2","50":"Inside Out 2","51":"The Bikeriders","52":"The Bikeriders","53":"Despicable Me 4","54":"The Bikeriders","55":"Despicable Me 4","56":"The Bikeriders","57":"Despicable Me 4","58":"Despicable Me 4","59":"Kung Fu Panda 4","60":"Firebrand","61":"Firebrand","62":"The Bikeriders","63":"The Bikeriders","64":"The Fall Guy","65":"The Bikeriders","66":"Kung Fu Panda 4","67":"The Fall Guy"},"Distributor":{"0":"Walt Disney Pictures","1":"Walt Disney Studios Motion Pictures","2":"","3":"Walt Disney Studios Motion Pictures","4":"Walt Disney Pictures","5":"Walt Disney Pictures","6":"Walt Disney Pictures","7":"Walt Disney Studios Motion Pictures","8":"Walt Disney Pictures","9":"Walt Disney Studios Motion Pictures","10":"Universal Pictures International (UPI)","11":"Walt Disney Pictures","12":"Walt Disney Pictures","13":"Avex Entertainment","14":"Walt Disney Pictures","15":"Walt Disney Pictures","16":"Walt Disney Pictures","17":"Walt Disney Pictures","18":"Walt Disney Pictures","19":"Walt Disney Pictures","20":"Walt Disney Pictures","21":"Walt Disney Pictures","22":"Walt Disney Pictures","23":"Walt Disney Pictures","24":"Walt Disney Pictures","25":"","26":"Walt Disney Pictures","27":"Walt Disney Pictures","28":"Walt Disney Pictures","29":"Walt Disney Pictures","30":"Walt Disney Pictures","31":"Universal Pictures International (UPI)","32":"Walt Disney Pictures","33":"Walt Disney Pictures","34":"Walt Disney Pictures","35":"","36":"Universal Pictures International (UPI)","37":"Universal Pictures International (UPI)","38":"Universal Pictures International (UPI)","39":"Universal Pictures International (UPI)","40":"Universal Pictures International (UPI)","41":"Forum Hungary","42":"Universal Pictures International (UPI)","43":"Universal Pictures International (UPI)","44":"","45":"Universal Pictures International (UPI)","46":"Universal Pictures International (UPI)","47":"Forum Film","48":"","49":"Sam Film","50":"","51":"Universal Pictures International (UPI)","52":"Universal Pictures International (UPI)","53":"Universal Pictures International (UPI)","54":"Universal Pictures International (UPI)","55":"Universal Pictures International (UPI)","56":"Universal Pictures International (UPI)","57":"Universal Pictures International (UPI)","58":"Universal Pictures International (UPI)","59":"Universal Pictures International (UPI)","60":"","61":"","62":"Universal Pictures International (UPI)","63":"Universal Pictures International (UPI)","64":"Universal Pictures International (UPI)","65":"Universal Pictures International (UPI)","66":"Universal Pictures International (UPI)","67":"Universal Pictures International (UPI)"},"Weekend Gross":{"0":9237667,"1":8769022,"2":7718795,"3":6694866,"4":6570115,"5":5037075,"6":4714295,"7":4258498,"8":4039683,"9":2916999,"10":1832982,"11":1821473,"12":1548075,"13":1378921,"14":1375451,"15":1207163,"16":1155580,"17":780387,"18":732264,"19":640075,"20":591075,"21":546370,"22":538635,"23":359196,"24":351020,"25":338138,"26":326142,"27":325949,"28":244144,"29":168932,"30":135597,"31":132506,"32":32161,"33":29254,"34":799,"35":1487409,"36":982395,"37":791244,"38":615222,"39":526888,"40":397116,"41":384777,"42":304970,"43":291274,"44":179695,"45":136122,"46":129578,"47":107997,"48":105945,"49":49265,"50":33836,"51":30953,"52":19740,"53":14144,"54":11379,"55":11042,"56":9831,"57":5333,"58":4602,"59":4582,"60":1450,"61":1251,"62":1204,"63":1067,"64":983,"65":851,"66":623,"67":177}}